skarp/__about__.py
skarp/__init__.py
skarp-0.0.1.dist-info/METADATA
skarp-0.0.1.dist-info/WHEEL
skarp-0.0.1.dist-info/licenses/LICENSE.txt
skarp-0.0.1.dist-info/RECORD
