Metadata-Version: 2.3
Name: skarp
Version: 0.0.1
Project-URL: Documentation, https://github.com/tunnelworks/skarp#readme
Project-URL: Issues, https://github.com/tunnelworks/skarp/issues
Project-URL: Source, https://github.com/tunnelworks/skarp
Author-email: tunnelworks <git@tunnelworks.org>
License-Expression: Apache-2.0
License-File: LICENSE.txt
Classifier: Development Status :: 2 - Pre-Alpha
Classifier: Programming Language :: Python
Classifier: Programming Language :: Python :: 3.8
Classifier: Programming Language :: Python :: 3.9
Classifier: Programming Language :: Python :: 3.10
Classifier: Programming Language :: Python :: 3.11
Classifier: Programming Language :: Python :: 3.12
Classifier: Programming Language :: Python :: Implementation :: CPython
Classifier: Programming Language :: Python :: Implementation :: PyPy
Requires-Python: >=3.8
